[
  {
    "id": 1,
    "name": "Sundarbans Mangrove Forest",
    "location": "Bangladesh/India",
    "image": "https://images.unsplash.com/photo-1544735716-392fe2489ffa?w=800",
    "yearsRemaining": 12,
    "threatLevel": "critical",
    "threats": ["Rising Sea Levels", "Deforestation", "Cyclones"],
    "culture": "Traditional honey collectors, tiger trackers, and boat communities",
    "witnesses": 847,
    "lastWitness": "2 days ago",
    "story": "Home to the Royal Bengal Tiger and ancient fishing communities practicing centuries-old traditions that will vanish with the rising tides.",
    "coordinates": [21.9497, 89.1833]
  },
  {
    "id": 2,
    "name": "Glacier Village of Shimshal",
    "location": "Pakistan",
    "image": "https://images.unsplash.com/photo-1464822759023-fed622ff2c3b?w=800",
    "yearsRemaining": 18,
    "threatLevel": "high",
    "threats": ["Glacial Melt", "Water Scarcity", "Youth Migration"],
    "culture": "Last yak herders of the Himalayas, ancient trade route guardians",
    "witnesses": 234,
    "lastWitness": "1 week ago",
    "story": "The highest settlement on the ancient Silk Road. Elders still speak a language with no written form, carrying stories that exist only in memory.",
    "coordinates": [36.4167, 75.5167]
  },
  {
    "id": 3,
    "name": "Isle de Jean Charles",
    "location": "Louisiana, USA",
    "image": "https://images.unsplash.com/photo-1500382017468-9049fed747ef?w=800",
    "yearsRemaining": 8,
    "threatLevel": "critical",
    "threats": ["Coastal Erosion", "Hurricane Damage", "Saltwater Intrusion"],
    "culture": "Biloxi-Chitimacha-Choctaw tribe, America's first climate refugees",
    "witnesses": 1203,
    "lastWitness": "3 hours ago",
    "story": "98% of the island has disappeared since 1955. The tribe that has lived here for generations is being forcibly relocated. Document their final days.",
    "coordinates": [29.4089, -90.3456]
  },
  {
    "id": 4,
    "name": "Tuvalu Islands",
    "location": "Pacific Ocean",
    "image": "https://images.unsplash.com/photo-1559128010-7c1ad6e1b6a5?w=800",
    "yearsRemaining": 25,
    "threatLevel": "high",
    "threats": ["Sea Level Rise", "Ocean Acidification", "Freshwater Loss"],
    "culture": "Polynesian navigation traditions, traditional fishing ceremonies",
    "witnesses": 567,
    "lastWitness": "5 days ago",
    "story": "An entire nation preparing to become the first country erased by climate change. Their government has already purchased land in Fiji for evacuation.",
    "coordinates": [-7.1095, 179.194]
  },
  {
    "id": 5,
    "name": "Ayoreo-Totobiegosode Territory",
    "location": "Paraguay",
    "image": "https://images.unsplash.com/photo-1516026672322-bc52d61a55d5?w=800",
    "yearsRemaining": 15,
    "threatLevel": "critical",
    "threats": ["Illegal Deforestation", "Cattle Ranching", "Contact Pressure"],
    "culture": "One of the last uncontacted tribes in South America",
    "witnesses": 89,
    "lastWitness": "1 month ago",
    "story": "Some members have never seen outsiders. Their forest home is being bulldozed for cattle. When they emerge, their 10,000-year-old way of life ends.",
    "coordinates": [-20.2167, -60.1667]
  },
  {
    "id": 6,
    "name": "Venice Historic Center",
    "location": "Italy",
    "image": "https://images.unsplash.com/photo-1523906834658-6e24ef2386f9?w=800",
    "yearsRemaining": 30,
    "threatLevel": "moderate",
    "threats": ["Acqua Alta Flooding", "Foundation Erosion", "Mass Tourism Exodus"],
    "culture": "Gondoliers, glass blowers of Murano, original Venetian families",
    "witnesses": 4521,
    "lastWitness": "1 hour ago",
    "story": "Only 50,000 original Venetians remain, down from 175,000 in 1950. The authentic Venice—not the tourist facade—is dying.",
    "coordinates": [45.4408, 12.3155]
  },
  {
    "id": 7,
    "name": "Dead Sea Shores",
    "location": "Israel/Jordan",
    "image": "https://images.unsplash.com/photo-1544551763-46a013bb70d5?w=800",
    "yearsRemaining": 20,
    "threatLevel": "high",
    "threats": ["Water Diversion", "Mineral Extraction", "Sinkholes"],
    "culture": "Ancient salt harvesting traditions, therapeutic mud traditions",
    "witnesses": 892,
    "lastWitness": "12 hours ago",
    "story": "Losing 1 meter of depth per year. The shoreline has retreated 30km. Hotels built in the 1980s now stand 2km from the water.",
    "coordinates": [31.5, 35.5]
  },
  {
    "id": 8,
    "name": "Aral Sea Fishing Villages",
    "location": "Kazakhstan/Uzbekistan",
    "image": "https://images.unsplash.com/photo-1506905925346-21bda4d32df4?w=800",
    "yearsRemaining": 5,
    "threatLevel": "critical",
    "threats": ["Complete Desiccation", "Toxic Dust Storms", "Economic Collapse"],
    "culture": "Ghost towns of former fishermen, ship graveyards in desert",
    "witnesses": 156,
    "lastWitness": "2 weeks ago",
    "story": "Once the 4th largest lake on Earth, now 90% gone. Rusting ships sit 100km from water. Last fishermen share stories of abundance.",
    "coordinates": [45.0, 59.0]
  },
  {
    "id": 9,
    "name": "Ganga Aarti Ghats of Varanasi",
    "location": "Uttar Pradesh, India",
    "image": "https://images.unsplash.com/photo-1561361513-2d000a50f0dc?w=800",
    "yearsRemaining": 15,
    "threatLevel": "high",
    "threats": ["River Pollution", "Urban Development", "Traditional Priest Migration"],
    "culture": "Ancient Brahmin families performing 3000-year-old rituals, traditional boat makers",
    "witnesses": 2341,
    "lastWitness": "4 hours ago",
    "story": "The sacred Ganga is dying. Ancient priest families are leaving as pollution makes traditional ceremonies impossible. The spiritual heart of Hinduism faces extinction.",
    "coordinates": [25.3176, 82.9739]
  },
  {
    "id": 10,
    "name": "Khonoma Village Green Terraces",
    "location": "Nagaland, India",
    "image": "https://images.unsplash.com/photo-1586500036706-41963de24d8b?w=800",
    "yearsRemaining": 20,
    "threatLevel": "moderate",
    "threats": ["Youth Migration", "Modern Agriculture", "Climate Change"],
    "culture": "Angami Naga tribe's sustainable farming, traditional warrior culture, headhunting stories",
    "witnesses": 234,
    "lastWitness": "1 week ago",
    "story": "India's first green village practices 700-year-old sustainable farming. Young people leave for cities, taking ancient knowledge with them.",
    "coordinates": [25.6751, 94.0169]
  },
  {
    "id": 11,
    "name": "Majuli River Island Monasteries",
    "location": "Assam, India",
    "image": "https://images.unsplash.com/photo-1578662996442-48f60103fc96?w=800",
    "yearsRemaining": 10,
    "threatLevel": "critical",
    "threats": ["River Erosion", "Flooding", "Monastery Abandonment"],
    "culture": "Vaishnavite monks, traditional mask making, Sattriya dance",
    "witnesses": 567,
    "lastWitness": "2 days ago",
    "story": "The world's largest river island is disappearing. 400-year-old monasteries are being swallowed by the Brahmaputra. Monks are the last keepers of dying arts.",
    "coordinates": [27.0538, 94.2146]
  },
  {
    "id": 12,
    "name": "Kutch Desert Salt Pans",
    "location": "Gujarat, India",
    "image": "https://images.unsplash.com/photo-1544735716-392fe2489ffa?w=800",
    "yearsRemaining": 25,
    "threatLevel": "moderate",
    "threats": ["Industrial Development", "Water Scarcity", "Traditional Knowledge Loss"],
    "culture": "Agariyas salt farmers, traditional salt harvesting, desert nomads",
    "witnesses": 445,
    "lastWitness": "3 days ago",
    "story": "Families have harvested salt here for 600 years. Industrial salt production and water scarcity threaten this ancient livelihood and the pristine white desert.",
    "coordinates": [23.7337, 69.8597]
  },
  {
    "id": 13,
    "name": "Spiti Valley Ancient Monasteries",
    "location": "Himachal Pradesh, India",
    "image": "https://images.unsplash.com/photo-1506905925346-21bda4d32df4?w=800",
    "yearsRemaining": 30,
    "threatLevel": "high",
    "threats": ["Climate Change", "Monk Migration", "Infrastructure Development"],
    "culture": "Tibetan Buddhist monks, ancient manuscripts, traditional medicine",
    "witnesses": 189,
    "lastWitness": "1 week ago",
    "story": "1000-year-old monasteries in the world's coldest desert. Rising temperatures melt permafrost, cracking ancient walls. Young monks leave for warmer regions.",
    "coordinates": [32.2432, 78.0322]
  },
  {
    "id": 14,
    "name": "Chilika Lake Fishing Villages",
    "location": "Odisha, India",
    "image": "https://images.unsplash.com/photo-1559128010-7c1ad6e1b6a5?w=800",
    "yearsRemaining": 18,
    "threatLevel": "high",
    "threats": ["Lake Shrinkage", "Aquaculture Pollution", "Cyclone Damage"],
    "culture": "Traditional fishermen, dolphin watchers, migratory bird guides",
    "witnesses": 678,
    "lastWitness": "5 hours ago",
    "story": "Asia's largest brackish water lagoon is shrinking. Traditional fishing communities lose their livelihood as the lake ecosystem collapses from pollution and climate change.",
    "coordinates": [19.7165, 85.3206]
  },
  {
    "id": 15,
    "name": "Hampi Ruins Living Heritage",
    "location": "Karnataka, India",
    "image": "https://images.unsplash.com/photo-1582510003544-4d00b7f74220?w=800",
    "yearsRemaining": 40,
    "threatLevel": "moderate",
    "threats": ["Stone Quarrying", "Tourist Damage", "Encroachment"],
    "culture": "Temple priests, traditional stone carvers, Vijayanagara descendants",
    "witnesses": 1234,
    "lastWitness": "6 hours ago",
    "story": "The last Vijayanagara Empire capital. Ancient families still perform rituals in 500-year-old temples. Illegal mining threatens the UNESCO World Heritage site.",
    "coordinates": [15.3350, 76.4600]
  },
  {
    "id": 16,
    "name": "Andaman Jarawa Tribal Reserves",
    "location": "Andaman Islands, India",
    "image": "https://images.unsplash.com/photo-1516026672322-bc52d61a55d5?w=800",
    "yearsRemaining": 12,
    "threatLevel": "critical",
    "threats": ["Outside Contact", "Poaching", "Disease Transmission"],
    "culture": "One of the last Stone Age tribes, traditional hunting, ancient language",
    "witnesses": 45,
    "lastWitness": "3 weeks ago",
    "story": "400 Jarawa people remain, living as their ancestors did 60,000 years ago. Each contact with outsiders risks destroying their immunity and culture forever.",
    "coordinates": [11.7401, 92.6586]
  },
  {
    "id": 17,
    "name": "Kerala Backwater Traditional Houseboats",
    "location": "Kerala, India",
    "image": "https://images.unsplash.com/photo-1602216056096-3b40cc0c9944?w=800",
    "yearsRemaining": 22,
    "threatLevel": "moderate",
    "threats": ["Water Pollution", "Modern Boat Industry", "Craftsman Migration"],
    "culture": "Traditional boat builders, coconut coir workers, backwater fishermen",
    "witnesses": 892,
    "lastWitness": "1 day ago",
    "story": "Families have built boats without nails for 800 years, using only coconut coir and wood. Pollution and modern materials threaten this ancient craft.",
    "coordinates": [9.4981, 76.3388]
  },
  {
    "id": 18,
    "name": "Thar Desert Camel Herders",
    "location": "Rajasthan, India",
    "image": "https://images.unsplash.com/photo-1544551763-46a013bb70d5?w=800",
    "yearsRemaining": 16,
    "threatLevel": "high",
    "threats": ["Mechanized Transport", "Water Scarcity", "Grazing Land Loss"],
    "culture": "Raika camel herders, traditional desert navigation, folk music",
    "witnesses": 334,
    "lastWitness": "4 days ago",
    "story": "Raika families have bred camels for 1000 years. Trucks replace camel caravans. The last nomadic herders struggle as ancient trade routes disappear.",
    "coordinates": [27.0238, 70.8022]
  },
  {
    "id": 19,
    "name": "Darjeeling Tea Garden Heritage",
    "location": "West Bengal, India",
    "image": "https://images.unsplash.com/photo-1578662996442-48f60103fc96?w=800",
    "yearsRemaining": 35,
    "threatLevel": "moderate",
    "threats": ["Climate Change", "Labor Migration", "Plantation Closure"],
    "culture": "Tea garden workers, traditional tea processing, Himalayan communities",
    "witnesses": 756,
    "lastWitness": "8 hours ago",
    "story": "150-year-old tea gardens face climate change. Rising temperatures push tea cultivation higher up mountains. Traditional workers' families face uncertain futures.",
    "coordinates": [27.0410, 88.2663]
  },
  {
    "id": 20,
    "name": "Goa Traditional Feni Distilleries",
    "location": "Goa, India",
    "image": "https://images.unsplash.com/photo-1506905925346-21bda4d32df4?w=800",
    "yearsRemaining": 28,
    "threatLevel": "moderate",
    "threats": ["Tourism Development", "Young Generation Disinterest", "Cashew Tree Decline"],
    "culture": "Traditional feni makers, cashew farmers, Portuguese-influenced culture",
    "witnesses": 423,
    "lastWitness": "2 days ago",
    "story": "Families distill feni from cashew and palm for 400 years. Tourism development replaces cashew groves with hotels. Ancient recipes risk being lost forever.",
    "coordinates": [15.2993, 74.1240]
  },
  {
    "id": 21,
    "name": "Ladakh High Altitude Villages",
    "location": "Ladakh, India",
    "image": "https://images.unsplash.com/photo-1464822759023-fed622ff2c3b?w=800",
    "yearsRemaining": 14,
    "threatLevel": "high",
    "threats": ["Glacial Melt", "Youth Migration", "Military Development"],
    "culture": "Buddhist farmers, traditional architecture, ancient trade routes",
    "witnesses": 267,
    "lastWitness": "1 week ago",
    "story": "Villages at 4000m altitude face water crisis as glaciers melt. Young people leave for cities. Ancient farming techniques that sustained life in the desert mountains are disappearing.",
    "coordinates": [34.1526, 77.5771]
  },
  {
    "id": 22,
    "name": "Mumbai Koli Fishing Communities",
    "location": "Mumbai, Maharashtra",
    "image": "https://images.unsplash.com/photo-1559128010-7c1ad6e1b6a5?w=800",
    "yearsRemaining": 20,
    "threatLevel": "high",
    "threats": ["Coastal Development", "Sea Pollution", "Fishing Ground Loss"],
    "culture": "Original Mumbai inhabitants, traditional fishing, coastal goddess worship",
    "witnesses": 1456,
    "lastWitness": "3 hours ago",
    "story": "Mumbai's original inhabitants, the Koli fishermen, are being pushed out by skyscrapers. Their 2000-year-old fishing traditions face extinction as the sea becomes too polluted.",
    "coordinates": [19.0760, 72.8777]
  },
  {
    "id": 23,
    "name": "Arunachal Pradesh Tribal Villages",
    "location": "Arunachal Pradesh, India",
    "image": "https://images.unsplash.com/photo-1516026672322-bc52d61a55d5?w=800",
    "yearsRemaining": 25,
    "threatLevel": "moderate",
    "threats": ["Modernization", "Language Loss", "Forest Degradation"],
    "culture": "26 different tribes, animist traditions, traditional crafts",
    "witnesses": 178,
    "lastWitness": "5 days ago",
    "story": "India's most linguistically diverse state. Each tribe has unique traditions. Modern education and migration threaten 26 distinct cultures and languages.",
    "coordinates": [28.2180, 94.7278]
  },
  {
    "id": 24,
    "name": "Pushkar Camel Fair Traditions",
    "location": "Rajasthan, India",
    "image": "https://images.unsplash.com/photo-1544551763-46a013bb70d5?w=800",
    "yearsRemaining": 30,
    "threatLevel": "moderate",
    "threats": ["Commercialization", "Camel Population Decline", "Traditional Trader Loss"],
    "culture": "Camel traders, folk musicians, traditional livestock dealers",
    "witnesses": 2134,
    "lastWitness": "2 weeks ago",
    "story": "1000-year-old camel fair becomes tourist spectacle. Real camel traders are outnumbered by tourists. Ancient livestock trading traditions are being commercialized out of existence.",
    "coordinates": [26.4899, 74.5511]
  },
  {
    "id": 25,
    "name": "Coorg Coffee Plantation Heritage",
    "location": "Karnataka, India",
    "image": "https://images.unsplash.com/photo-1578662996442-48f60103fc96?w=800",
    "yearsRemaining": 20,
    "threatLevel": "moderate",
    "threats": ["Climate Change", "Plantation Conversion", "Traditional Knowledge Loss"],
    "culture": "Kodava coffee growers, traditional processing methods, estate workers",
    "witnesses": 567,
    "lastWitness": "1 day ago",
    "story": "150-year-old family coffee estates face climate change. Rising temperatures push coffee cultivation to higher altitudes. Traditional shade-grown methods are being abandoned.",
    "coordinates": [12.3375, 75.8069]
  },
  {
    "id": 26,
    "name": "Konark Sun Temple Stone Carvers",
    "location": "Odisha, India",
    "image": "https://images.unsplash.com/photo-1582510003544-4d00b7f74220?w=800",
    "yearsRemaining": 35,
    "threatLevel": "moderate",
    "threats": ["Artisan Migration", "Modern Construction", "Skill Loss"],
    "culture": "Traditional stone carvers, temple sculptors, ancient techniques",
    "witnesses": 234,
    "lastWitness": "3 days ago",
    "story": "Families who carved the Sun Temple for generations now work in modern construction. Ancient stone carving techniques that created UNESCO wonders are disappearing.",
    "coordinates": [19.8876, 86.0947]
  },
  {
    "id": 27,
    "name": "Rann of Kutch Salt Workers",
    "location": "Gujarat, India",
    "image": "https://images.unsplash.com/photo-1544735716-392fe2489ffa?w=800",
    "yearsRemaining": 18,
    "threatLevel": "high",
    "threats": ["Industrial Salt Production", "Water Scarcity", "Youth Migration"],
    "culture": "Agariyas salt farmers, traditional salt harvesting, desert survival skills",
    "witnesses": 445,
    "lastWitness": "2 days ago",
    "story": "Families harvest salt from the white desert for 600 years. Industrial production and water scarcity threaten this ancient livelihood in the world's largest salt desert.",
    "coordinates": [23.7337, 69.8597]
  },
  {
    "id": 28,
    "name": "Banaras Silk Weavers",
    "location": "Uttar Pradesh, India",
    "image": "https://images.unsplash.com/photo-1578662996442-48f60103fc96?w=800",
    "yearsRemaining": 25,
    "threatLevel": "high",
    "threats": ["Machine Production", "Cheap Imports", "Weaver Poverty"],
    "culture": "Traditional silk weavers, Banarasi saree makers, family looms",
    "witnesses": 1234,
    "lastWitness": "6 hours ago",
    "story": "Families weave silk for 500 years in narrow Varanasi lanes. Machine-made sarees and cheap imports force master weavers into poverty. Ancient patterns risk being lost forever.",
    "coordinates": [25.3176, 82.9739]
  },
  {
    "id": 29,
    "name": "Nilgiri Mountain Railway Heritage",
    "location": "Tamil Nadu, India",
    "image": "https://images.unsplash.com/photo-1506905925346-21bda4d32df4?w=800",
    "yearsRemaining": 40,
    "threatLevel": "moderate",
    "threats": ["Modernization Pressure", "Maintenance Costs", "Safety Concerns"],
    "culture": "Steam engine operators, traditional railway workers, hill station heritage",
    "witnesses": 892,
    "lastWitness": "1 week ago",
    "story": "130-year-old toy train climbs through tea gardens using steam technology. Pressure to modernize threatens this UNESCO World Heritage railway and its traditional operations.",
    "coordinates": [11.4064, 76.6932]
  },
  {
    "id": 30,
    "name": "Khasi Living Root Bridges",
    "location": "Meghalaya, India",
    "image": "https://images.unsplash.com/photo-1516026672322-bc52d61a55d5?w=800",
    "yearsRemaining": 50,
    "threatLevel": "moderate",
    "threats": ["Modern Bridge Construction", "Youth Migration", "Knowledge Loss"],
    "culture": "Khasi tribe, traditional bridge builders, forest guardians",
    "witnesses": 345,
    "lastWitness": "4 days ago",
    "story": "Khasi people grow bridges from living tree roots over 15 years. Modern concrete bridges and youth migration threaten this unique 500-year-old bio-engineering tradition.",
    "coordinates": [25.2993, 91.8854]
  },
  {
    "id": 31,
    "name": "Bishnoi Wildlife Conservation Villages",
    "location": "Rajasthan, India",
    "image": "https://images.unsplash.com/photo-1544551763-46a013bb70d5?w=800",
    "yearsRemaining": 30,
    "threatLevel": "moderate",
    "threats": ["Urbanization", "Water Scarcity", "Traditional Practice Erosion"],
    "culture": "Bishnoi community, wildlife protectors, traditional conservation",
    "witnesses": 567,
    "lastWitness": "2 days ago",
    "story": "Bishnoi people protect wildlife for 500 years, never cutting green trees or killing animals. Modern development and water scarcity threaten their conservation villages.",
    "coordinates": [27.3389, 72.9831]
  },
  {
    "id": 32,
    "name": "Chettinad Mansion Architecture",
    "location": "Tamil Nadu, India",
    "image": "https://images.unsplash.com/photo-1582510003544-4d00b7f74220?w=800",
    "yearsRemaining": 25,
    "threatLevel": "high",
    "threats": ["Mansion Abandonment", "Skilled Craftsman Loss", "Material Scarcity"],
    "culture": "Chettiar merchants, traditional architects, lime mortar specialists",
    "witnesses": 234,
    "lastWitness": "1 week ago",
    "story": "Merchant families built 10,000 mansions with materials from around the world. Families migrate to cities, leaving architectural marvels to decay. Traditional building skills are dying.",
    "coordinates": [10.0889, 78.5933]
  },
  {
    "id": 33,
    "name": "Toda Tribal Dairy Traditions",
    "location": "Tamil Nadu, India",
    "image": "https://images.unsplash.com/photo-1516026672322-bc52d61a55d5?w=800",
    "yearsRemaining": 15,
    "threatLevel": "critical",
    "threats": ["Population Decline", "Modernization", "Sacred Grove Loss"],
    "culture": "Toda tribe, sacred buffalo herding, traditional dairy practices",
    "witnesses": 89,
    "lastWitness": "3 weeks ago",
    "story": "Only 1,600 Toda people remain in Nilgiri hills. Their sacred relationship with buffalo and unique dairy traditions face extinction as young people adopt modern lifestyles.",
    "coordinates": [11.3410, 76.7337]
  },
  {
    "id": 34,
    "name": "Jaisalmer Havelis Stone Craft",
    "location": "Rajasthan, India",
    "image": "https://images.unsplash.com/photo-1582510003544-4d00b7f74220?w=800",
    "yearsRemaining": 35,
    "threatLevel": "moderate",
    "threats": ["Tourism Pressure", "Skilled Artisan Migration", "Sandstone Quarrying Restrictions"],
    "culture": "Traditional stone carvers, haveli builders, desert architects",
    "witnesses": 678,
    "lastWitness": "5 days ago",
    "story": "Families carved golden sandstone havelis for 800 years. Tourism pressure and quarrying restrictions threaten the craft that built the Golden City's architectural wonders.",
    "coordinates": [26.9157, 70.9083]
  },
  {
    "id": 35,
    "name": "Manipur Loktak Lake Fishing Villages",
    "location": "Manipur, India",
    "image": "https://images.unsplash.com/photo-1559128010-7c1ad6e1b6a5?w=800",
    "yearsRemaining": 12,
    "threatLevel": "critical",
    "threats": ["Lake Pollution", "Phumdi Destruction", "Dam Impact"],
    "culture": "Traditional fishermen, floating hut dwellers, lake ecosystem guardians",
    "witnesses": 156,
    "lastWitness": "1 week ago",
    "story": "Fishermen live on floating biomass islands for centuries. Pollution and dam construction destroy the unique ecosystem. The world's only floating national park faces collapse.",
    "coordinates": [24.5595, 93.7997]
  },
  {
    "id": 36,
    "name": "Warli Tribal Art Villages",
    "location": "Maharashtra, India",
    "image": "https://images.unsplash.com/photo-1516026672322-bc52d61a55d5?w=800",
    "yearsRemaining": 20,
    "threatLevel": "moderate",
    "threats": ["Commercialization", "Traditional Context Loss", "Youth Migration"],
    "culture": "Warli tribe, traditional wall painters, ritual art practices",
    "witnesses": 445,
    "lastWitness": "3 days ago",
    "story": "Warli people paint their stories on mud walls for 3,000 years. Commercial art market strips away ritual meaning. Traditional village context disappears as youth migrate to cities.",
    "coordinates": [19.7515, 72.8636]
  },
  {
    "id": 37,
    "name": "Sikkim Monastery Mask Dance Traditions",
    "location": "Sikkim, India",
    "image": "https://images.unsplash.com/photo-1506905925346-21bda4d32df4?w=800",
    "yearsRemaining": 25,
    "threatLevel": "moderate",
    "threats": ["Monk Migration", "Tourism Commercialization", "Traditional Knowledge Loss"],
    "culture": "Buddhist monks, traditional mask makers, sacred dance performers",
    "witnesses": 234,
    "lastWitness": "2 weeks ago",
    "story": "Monks perform sacred Cham dances in 400-year-old monasteries. Young monks leave for modern education. Ancient mask-making and dance traditions risk disappearing from Himalayan valleys.",
    "coordinates": [27.5330, 88.5122]
  },
  {
    "id": 38,
    "name": "Pulicat Lake Traditional Fishing",
    "location": "Andhra Pradesh, India",
    "image": "https://images.unsplash.com/photo-1559128010-7c1ad6e1b6a5?w=800",
    "yearsRemaining": 18,
    "threatLevel": "high",
    "threats": ["Lake Shrinkage", "Industrial Pollution", "Cyclone Damage"],
    "culture": "Traditional fishermen, flamingo watchers, salt pan workers",
    "witnesses": 567,
    "lastWitness": "4 days ago",
    "story": "India's second-largest brackish water lake supports 20,000 fishermen. Industrial pollution and climate change shrink the lake. Traditional fishing communities face displacement.",
    "coordinates": [13.6288, 80.3214]
  },
  {
    "id": 39,
    "name": "Jharkhand Tribal Iron Smelting",
    "location": "Jharkhand, India",
    "image": "https://images.unsplash.com/photo-1516026672322-bc52d61a55d5?w=800",
    "yearsRemaining": 10,
    "threatLevel": "critical",
    "threats": ["Industrial Mining", "Forest Loss", "Traditional Knowledge Extinction"],
    "culture": "Asur tribe, traditional iron smelters, forest metal workers",
    "witnesses": 67,
    "lastWitness": "1 month ago",
    "story": "Asur tribe smelts iron using 2,000-year-old techniques in forest furnaces. Mining destroys their forests. The last traditional iron smelters in India face extinction.",
    "coordinates": [23.6102, 85.2799]
  },
  {
    "id": 40,
    "name": "Channapatna Wooden Toy Makers",
    "location": "Karnataka, India",
    "image": "https://images.unsplash.com/photo-1578662996442-48f60103fc96?w=800",
    "yearsRemaining": 22,
    "threatLevel": "moderate",
    "threats": ["Plastic Toy Competition", "Artisan Migration", "Raw Material Scarcity"],
    "culture": "Traditional toy makers, lacquer workers, wooden craft families",
    "witnesses": 345,
    "lastWitness": "2 days ago",
    "story": "Families carve wooden toys for 200 years using natural lacquer. Plastic toys flood markets. Traditional artisans struggle as children prefer electronic toys over handmade wooden ones.",
    "coordinates": [12.6518, 77.2069]
  }
]
